ladder/__init__.py
ladder/config.py
ladder/data_gen/__init__.py
ladder/data_gen/callbacks.py
ladder/data_gen/generator.py
ladder/data_gen/schema.py
ladder/data_gen/steps.py
ladder/engines/__init__.py
ladder/engines/difficulty_engine.py
ladder/engines/llm_engine.py
ladder/engines/verification_engine.py
ladder/evaluate/__init__.py
ladder/evaluate/benchmarking.py
ladder/evaluate/eval.py
ladder/finetuning/__init__.py
ladder/finetuning/grpo.py
ladder/finetuning/ladder.py
ladder/finetuning/ttrl.py
ladder/llms.py
ladder/schema.py
ladder/use_cases/__init__.py
ladder/use_cases/graph.py
ladder/utils.py
ladder_ai-0.1.94.dist-info/METADATA
ladder_ai-0.1.94.dist-info/WHEEL
ladder_ai-0.1.94.dist-info/entry_points.txt
ladder_ai-0.1.94.dist-info/RECORD
