Metadata-Version: 2.1
Name: ladder-ai
Version: 0.1.94
Summary: Ladder + TTFT LLM Finetuning
Author-Email: abdelrahman abounida <abdelrahmanaboneda@gmail.com>
License: MIT
Requires-Python: >=3.11
Requires-Dist: typing-extensions>=4.13.2
Requires-Dist: loguru>=0.7.3
Requires-Dist: pydantic>=2.11.3
Requires-Dist: dspy>=2.6.5
Requires-Dist: python-dotenv>=1.1.0
Requires-Dist: pandas>=2.2.3
